slicecap.py
slicecap-0.3.0.dist-info/licenses/LICENSE
slicecap-0.3.0.dist-info/METADATA
slicecap-0.3.0.dist-info/WHEEL
slicecap-0.3.0.dist-info/entry_points.txt
slicecap-0.3.0.dist-info/top_level.txt
slicecap-0.3.0.dist-info/RECORD
