Metadata-Version: 2.4
Name: slicecap
Version: 0.3.0
Summary: Slice a pcap file into pieces and process in parallel
Home-page: https://github.com/keiichishima/slicecap/
Author: Keiichi SHIMA
Author-email: keiichi@iijlab.net
License: BSD License
Classifier: Development Status :: 4 - Beta
Classifier: Environment :: Console
Classifier: Intended Audience :: Developers
Classifier: Intended Audience :: Information Technology
Classifier: Intended Audience :: Science/Research
Classifier: Intended Audience :: System Administrators
Classifier: License :: OSI Approved :: BSD License
Classifier: Programming Language :: Python :: 3.13
Classifier: Topic :: Scientific/Engineering :: Information Analysis
Classifier: Topic :: System :: Networking
Classifier: Topic :: Utilities
Requires-Python: >=3.13
License-File: LICENSE
Dynamic: author
Dynamic: author-email
Dynamic: classifier
Dynamic: description
Dynamic: home-page
Dynamic: license
Dynamic: license-file
Dynamic: requires-python
Dynamic: summary
